homey-stubs/__init__.pyi
homey-stubs/api.pyi
homey-stubs/api_app.pyi
homey-stubs/app.pyi
homey-stubs/ble_advertisement.pyi
homey-stubs/ble_characteristic.pyi
homey-stubs/ble_descriptor.pyi
homey-stubs/ble_peripheral.pyi
homey-stubs/ble_service.pyi
homey-stubs/cloud_oauth2_callback.pyi
homey-stubs/cloud_webhook.pyi
homey-stubs/device.pyi
homey-stubs/discovery_result.pyi
homey-stubs/discovery_result_mac.pyi
homey-stubs/discovery_result_mdns_sd.pyi
homey-stubs/discovery_result_ssdp.pyi
homey-stubs/discovery_strategy.pyi
homey-stubs/driver.pyi
homey-stubs/flow_argument.pyi
homey-stubs/flow_card.pyi
homey-stubs/flow_card_action.pyi
homey-stubs/flow_card_condition.pyi
homey-stubs/flow_card_trigger.pyi
homey-stubs/flow_card_trigger_device.pyi
homey-stubs/flow_token.pyi
homey-stubs/homey.pyi
homey-stubs/image.pyi
homey-stubs/insights_log.pyi
homey-stubs/pair_session.pyi
homey-stubs/signal.pyi
homey-stubs/signal_433.pyi
homey-stubs/signal_868.pyi
homey-stubs/signal_infrared.pyi
homey-stubs/simple_class.pyi
homey-stubs/video.pyi
homey-stubs/video_dash.pyi
homey-stubs/video_hls.pyi
homey-stubs/video_other.pyi
homey-stubs/video_rtmp.pyi
homey-stubs/video_rtsp.pyi
homey-stubs/video_web_rtc.pyi
homey-stubs/video_with_url.pyi
homey-stubs/widget.pyi
homey-stubs/widget_setting.pyi
homey-stubs/zigbee_node.pyi
homey-stubs/zwave_command_class.pyi
homey-stubs/zwave_node.pyi
homey-stubs/exceptions/__init__.pyi
homey-stubs/manager/__init__.pyi
homey-stubs/manager/api.pyi
homey-stubs/manager/apps.pyi
homey-stubs/manager/arp.pyi
homey-stubs/manager/ble.pyi
homey-stubs/manager/clock.pyi
homey-stubs/manager/cloud.pyi
homey-stubs/manager/dashboards.pyi
homey-stubs/manager/discovery.pyi
homey-stubs/manager/drivers.pyi
homey-stubs/manager/flow.pyi
homey-stubs/manager/geolocation.pyi
homey-stubs/manager/i18n.pyi
homey-stubs/manager/images.pyi
homey-stubs/manager/insights.pyi
homey-stubs/manager/notifications.pyi
homey-stubs/manager/rf.pyi
homey-stubs/manager/settings.pyi
homey_stubs-0.0.1.0.dist-info/METADATA
homey_stubs-0.0.1.0.dist-info/WHEEL
homey_stubs-0.0.1.0.dist-info/RECORD
