Metadata-Version: 2.4
Name: homey-stubs
Version: 0.0.1.0
Summary: Type annotations for the Homey SDK
Project-URL: homepage, https://homey.app/
Project-URL: documentation, https://apps.developer.homey.app/
Author: Athom B.V.
License-Expression: ISC
Keywords: homey,homey-stubs,mypy,pyright,smart home,smarthome,stubs,typing
Classifier: Intended Audience :: Developers
Classifier: License :: OSI Approved
Classifier: License :: OSI Approved :: ISC License (ISCL)
Classifier: Natural Language :: English
Classifier: Operating System :: OS Independent
Classifier: Programming Language :: Python
Classifier: Programming Language :: Python :: 3
Classifier: Programming Language :: Python :: 3.13
Classifier: Typing :: Stubs Only
Requires-Python: ==3.13.*
